setup.py
farm_db_handler/__init__.py
farm_db_handler.egg-info/PKG-INFO
farm_db_handler.egg-info/SOURCES.txt
farm_db_handler.egg-info/dependency_links.txt
farm_db_handler.egg-info/not-zip-safe
farm_db_handler.egg-info/top_level.txt