Metadata-Version: 1.0
Name: farm-db-handler
Version: 0.1
Summary: Database handler
Home-page: https://bitbucket.org/alectryonfarm/farm_db_handler
Author: Alectryon
Author-email: mbiedler@gmail.com
License: MIT
Platform: UNKNOWN
